{
  "appNotification" : {
    "_id" : "wm-appErrorHandler-wm.NotificationVariable-1454664620943",
    "name" : "appNotification",
    "owner" : "App",
    "category" : "wm.NotificationVariable",
    "dataBinding" : [ {
      "target" : "class",
      "value" : "Error",
      "type" : "list"
    }, {
      "target" : "toasterPosition",
      "value" : "bottom right",
      "type" : "list"
    } ],
    "operation" : "toast"
  },
  "goToPage_EditAccount" : {
    "_id" : "wm-goToPage_EditAccount-wm.NavigationVariable-1543871702019",
    "name" : "goToPage_EditAccount",
    "owner" : "App",
    "category" : "wm.NavigationVariable",
    "dataBinding" : [ ],
    "operation" : "gotoPage",
    "pageName" : "EditAccount",
    "dataSet" : [ ],
    "pageTransitions" : "none"
  },
  "goToPage_Main" : {
    "_id" : "wm-wm.NavigationVariable1389180517517",
    "name" : "goToPage_Main",
    "owner" : "App",
    "category" : "wm.NavigationVariable",
    "operation" : "gotoPage",
    "pageName" : "Main"
  },
  "goToPage_Parts" : {
    "_id" : "wm-goToPage_Parts-wm.NavigationVariable-1547085377985",
    "name" : "goToPage_Parts",
    "owner" : "App",
    "category" : "wm.NavigationVariable",
    "dataBinding" : [ ],
    "operation" : "gotoPage",
    "pageName" : "Parts",
    "dataSet" : [ ],
    "pageTransitions" : "none"
  },
  "loggedInUser" : {
    "_id" : "wm-loggedInUser-wm.Variable-1541186705549",
    "name" : "loggedInUser",
    "owner" : "App",
    "category" : "wm.Variable",
    "dataBinding" : [ ],
    "dataSet" : {
      "name" : "",
      "id" : "",
      "tenantId" : "",
      "isAuthenticated" : false,
      "isSecurityEnabled" : true,
      "roles" : [ ]
    },
    "type" : "string",
    "isList" : false,
    "saveInPhonegap" : false
  },
  "loginAction" : {
    "_id" : "wm-loginAction-wm.LoginVariable-1541186705549",
    "name" : "loginAction",
    "owner" : "App",
    "category" : "wm.LoginVariable",
    "dataBinding" : [ {
      "target" : "username",
      "value" : "bind:Widgets.usernametext.datavalue",
      "type" : "string"
    }, {
      "target" : "password",
      "value" : "bind:Widgets.passwordtext.datavalue",
      "type" : "string"
    }, {
      "target" : "rememberme",
      "value" : "bind:Widgets.remembermecheck.datavalue",
      "type" : "boolean"
    } ],
    "dataSet" : {
      "username" : "",
      "password" : "",
      "rememberme" : false
    },
    "type" : "string",
    "saveInPhonegap" : false,
    "startUpdate" : false,
    "autoUpdate" : false,
    "inFlightBehavior" : "executeLast",
    "transformationRequired" : false,
    "useDefaultSuccessHandler" : true
  },
  "logoutAction" : {
    "_id" : "wm-logoutAction-wm.LogoutVariable-1541186705549",
    "name" : "logoutAction",
    "owner" : "App",
    "category" : "wm.LogoutVariable",
    "type" : "string",
    "saveInPhonegap" : false,
    "inFlightBehavior" : "executeLast",
    "transformationRequired" : false,
    "redirectTo" : "Login",
    "useDefaultSuccessHandler" : true
  },
  "selectedEquipment" : {
    "_id" : "wm-selectedEquipment-wm.Variable-1541381576052",
    "name" : "selectedEquipment",
    "owner" : "App",
    "category" : "wm.Variable",
    "dataBinding" : [ ],
    "dataSet" : {
      "serial" : "",
      "idequipment" : "",
      "vendor" : "",
      "tenantId" : "",
      "description" : "",
      "vendorId" : ""
    },
    "type" : "com.huboem.arolcustomerportal.Equipment",
    "isList" : false,
    "saveInPhonegap" : false
  },
  "supportedLocale" : {
    "_id" : "wm-wm.Variable1402640443182",
    "name" : "supportedLocale",
    "owner" : "App",
    "category" : "wm.Variable",
    "dataSet" : {
      "en" : "English"
    },
    "type" : "string",
    "isList" : false,
    "saveInPhonegap" : false
  }
}